{
  "name": "PetParent",
  "options": {
    "idInjection": false,
    "mssql": {
      "schema": "dbo",
      "table": "PetParent"
    }
  },
  "properties": {
    "PetParentID": {
      "type": "Number",
      "id": 1,
      "required": true,
      "length": null,
      "precision": 10,
      "scale": 0,
      "mssql": {
        "columnName": "PetParentID",
        "dataType": "int",
        "dataLength": null,
        "dataPrecision": 10,
        "dataScale": 0,
        "nullable": "NO"
      }
    },
    "Name": {
      "type": "String",
      "required": false,
      "length": 150,
      "precision": null,
      "scale": null,
      "mssql": {
        "columnName": "Name",
        "dataType": "varchar",
        "dataLength": 150,
        "dataPrecision": null,
        "dataScale": null,
        "nullable": "YES"
      }
    },
    "Surname": {
      "type": "String",
      "required": false,
      "length": 255,
      "precision": null,
      "scale": null,
      "mssql": {
        "columnName": "Surname",
        "dataType": "varchar",
        "dataLength": 255,
        "dataPrecision": null,
        "dataScale": null,
        "nullable": "YES"
      }
    },
    "EmailAddress": {
      "type": "String",
      "required": false,
      "length": 255,
      "precision": null,
      "scale": null,
      "mssql": {
        "columnName": "EmailAddress",
        "dataType": "varchar",
        "dataLength": 255,
        "dataPrecision": null,
        "dataScale": null,
        "nullable": "YES"
      }
    },
    "PhoneNr": {
      "type": "Number",
      "required": false,
      "length": null,
      "precision": 10,
      "scale": 0,
      "mssql": {
        "columnName": "PhoneNr",
        "dataType": "numeric",
        "dataLength": null,
        "dataPrecision": 10,
        "dataScale": 0,
        "nullable": "YES"
      }
    },
    "ParentAddress": {
      "type": "String",
      "required": false,
      "length": -1,
      "precision": null,
      "scale": null,
      "mssql": {
        "columnName": "ParentAddress",
        "dataType": "varchar",
        "dataLength": -1,
        "dataPrecision": null,
        "dataScale": null,
        "nullable": "YES"
      }
    },
    "ParentPassword": {
      "type": "String",
      "required": false,
      "length": -1,
      "precision": null,
      "scale": null,
      "mssql": {
        "columnName": "ParentPassword",
        "dataType": "varchar",
        "dataLength": -1,
        "dataPrecision": null,
        "dataScale": null,
        "nullable": "YES"
      }
    },
    "Pets": {
      "type": "String",
      "required": false,
      "length": -1,
      "precision": null,
      "scale": null,
      "mssql": {
        "columnName": "Pets",
        "dataType": "varchar",
        "dataLength": -1,
        "dataPrecision": null,
        "dataScale": null,
        "nullable": "YES"
      }
    },
    "SuburbID": {
      "type": "Number",
      "required": false,
      "length": null,
      "precision": 10,
      "scale": 0,
      "mssql": {
        "columnName": "SuburbID",
        "dataType": "int",
        "dataLength": null,
        "dataPrecision": 10,
        "dataScale": 0,
        "nullable": "YES"
      }
    },
    "DiscoveryTypeID": {
      "type": "Number",
      "required": false,
      "length": null,
      "precision": 10,
      "scale": 0,
      "mssql": {
        "columnName": "DiscoveryTypeID",
        "dataType": "int",
        "dataLength": null,
        "dataPrecision": 10,
        "dataScale": 0,
        "nullable": "YES"
      }
    },
    "TitleID": {
      "type": "Number",
      "required": false,
      "length": null,
      "precision": 10,
      "scale": 0,
      "mssql": {
        "columnName": "TitleID",
        "dataType": "int",
        "dataLength": null,
        "dataPrecision": 10,
        "dataScale": 0,
        "nullable": "YES"
      }
    },
    "UserRoleID": {
      "type": "Number",
      "required": false,
      "length": null,
      "precision": 10,
      "scale": 0,
      "mssql": {
        "columnName": "UserRoleID",
        "dataType": "int",
        "dataLength": null,
        "dataPrecision": 10,
        "dataScale": 0,
        "nullable": "YES"
      }
    },
    "CityID": {
      "type": "Number",
      "required": false,
      "length": null,
      "precision": 10,
      "scale": 0,
      "mssql": {
        "columnName": "CityID",
        "dataType": "int",
        "dataLength": null,
        "dataPrecision": 10,
        "dataScale": 0,
        "nullable": "YES"
      }
    },
    "ProvinceID": {
      "type": "Number",
      "required": false,
      "length": null,
      "precision": 10,
      "scale": 0,
      "mssql": {
        "columnName": "ProvinceID",
        "dataType": "int",
        "dataLength": null,
        "dataPrecision": 10,
        "dataScale": 0,
        "nullable": "YES"
      }
    }
  },
  "validations": [],
  "relations": {},
  "acls": [],
  "methods": {}
}
