{
  "name": "ServiceType",
  "options": {
    "idInjection": false,
    "mssql": {
      "schema": "dbo",
      "table": "ServiceType"
    }
  },
  "properties": {
    "TypeID": {
      "type": "Number",
      "id": 1,
      "required": true,
      "length": null,
      "precision": 10,
      "scale": 0,
      "mssql": {
        "columnName": "TypeID",
        "dataType": "int",
        "dataLength": null,
        "dataPrecision": 10,
        "dataScale": 0,
        "nullable": "NO"
      }
    },
    "ServiceTypeDescription": {
      "type": "String",
      "required": true,
      "length": 50,
      "precision": null,
      "scale": null,
      "mssql": {
        "columnName": "ServiceTypeDescription",
        "dataType": "varchar",
        "dataLength": 50,
        "dataPrecision": null,
        "dataScale": null,
        "nullable": "NO"
      }
    },
    "PriceID": {
      "type": "Number",
      "required": false,
      "length": null,
      "precision": 10,
      "scale": 0,
      "mssql": {
        "columnName": "PriceID",
        "dataType": "int",
        "dataLength": null,
        "dataPrecision": 10,
        "dataScale": 0,
        "nullable": "YES"
      }
    }
  },
  "validations": [],
  "relations": {},
  "acls": [],
  "methods": {}
}
